mistralai_workflows/__init__.py
mistralai_workflows/client.py
mistralai_workflows/exceptions.py
mistralai_workflows/exports.py
mistralai_workflows/py.typed
mistralai_workflows/common/models.py
mistralai_workflows/core/__init__.py
mistralai_workflows/core/activity.py
mistralai_workflows/core/interactive_workflow.py
mistralai_workflows/core/logging.py
mistralai_workflows/core/worker.py
mistralai_workflows/core/workflow.py
mistralai_workflows/core/config/__init__.py
mistralai_workflows/core/config/config.py
mistralai_workflows/core/config/config_discovery.py
mistralai_workflows/core/definition/__init__.py
mistralai_workflows/core/definition/workflow_definition.py
mistralai_workflows/core/definition/validation/__init__.py
mistralai_workflows/core/definition/validation/parameter_conversion.py
mistralai_workflows/core/definition/validation/schema_generator.py
mistralai_workflows/core/definition/validation/validator.py
mistralai_workflows/core/dependencies/__init__.py
mistralai_workflows/core/dependencies/dependency_injector.py
mistralai_workflows/core/encoding/__init__.py
mistralai_workflows/core/encoding/fields_offloader.py
mistralai_workflows/core/encoding/payload_encoder.py
mistralai_workflows/core/events/__init__.py
mistralai_workflows/core/events/event_activities.py
mistralai_workflows/core/events/event_context.py
mistralai_workflows/core/events/event_interceptor.py
mistralai_workflows/core/events/event_utils.py
mistralai_workflows/core/events/json_patch.py
mistralai_workflows/core/execution/__init__.py
mistralai_workflows/core/execution/local_activity.py
mistralai_workflows/core/execution/workflow_execution.py
mistralai_workflows/core/execution/concurrency/__init__.py
mistralai_workflows/core/execution/concurrency/concurrency_workflow.py
mistralai_workflows/core/execution/concurrency/execute_activities_in_batch.py
mistralai_workflows/core/execution/concurrency/execute_activities_in_parallel.py
mistralai_workflows/core/execution/concurrency/run_in_batches.py
mistralai_workflows-2.0.0rc12.dist-info/METADATA
mistralai_workflows-2.0.0rc12.dist-info/WHEEL
mistralai_workflows-2.0.0rc12.dist-info/licenses/LICENSE
mistralai_workflows-2.0.0rc12.dist-info/RECORD
