Metadata-Version: 2.4
Name: mistralai-workflows
Version: 2.0.0rc12
Summary: Mistral Workflows - Build reliable AI workflows with Python
Project-URL: Homepage, https://mistral.ai
Project-URL: Documentation, https://docs-internal-frameworks.mistral.ai/workflows
Author-email: Mistral AI <support@mistral.ai>
License: Apache-2.0
License-File: LICENSE
Keywords: ai,llm,mistral,orchestration,temporal,workflows
Classifier: Development Status :: 4 - Beta
Classifier: Intended Audience :: Developers
Classifier: License :: OSI Approved :: Apache Software License
Classifier: Programming Language :: Python :: 3
Classifier: Programming Language :: Python :: 3.12
Classifier: Topic :: Scientific/Engineering :: Artificial Intelligence
Classifier: Topic :: Software Development :: Libraries :: Python Modules
Requires-Python: <3.13,>=3.12
Requires-Dist: aioboto3<13.0.0,>=12.4.0
Requires-Dist: aiocache>=0.12.3
Requires-Dist: asynciolimiter>=1.2.0
Requires-Dist: authlib>=1.6.5
Requires-Dist: azure-storage-blob[aio]<12.25.0,>=12.24.0
Requires-Dist: cryptography>=41.0.0
Requires-Dist: gcloud-aio-storage<10.0.0,>=9.3.0
Requires-Dist: griffe>=1.14.0
Requires-Dist: httpx>=0.27.0
Requires-Dist: jinja2>=3.1.6
Requires-Dist: jsonpatch>=1.33
Requires-Dist: mcp>=1.12.4
Requires-Dist: mistralai>=1.8.1
Requires-Dist: nats-py>=2.10.0
Requires-Dist: opentelemetry-api<2.0.0,>=1.30.0
Requires-Dist: opentelemetry-exporter-otlp-proto-http<2.0.0,>=1.30.0
Requires-Dist: opentelemetry-instrumentation-aiohttp-client<0.59,>=0.51b0
Requires-Dist: opentelemetry-instrumentation-asyncio<0.59,>=0.51b0
Requires-Dist: opentelemetry-instrumentation-fastapi<0.59,>=0.51b0
Requires-Dist: opentelemetry-instrumentation-httpx<0.59,>=0.51b0
Requires-Dist: opentelemetry-sdk<2.0.0,>=1.30.0
Requires-Dist: orjson<4.0.0,>=3.10.15
Requires-Dist: pydantic-settings>=2.7.1
Requires-Dist: pydantic>=2.12.0
Requires-Dist: structlog<26,>=24
Requires-Dist: temporalio==1.18.1
Requires-Dist: tenacity>=9.1.2
Requires-Dist: tqdm>=4.67.1
Requires-Dist: types-tqdm>=4.67.0.20250516
Provides-Extra: agents
Requires-Dist: mistralai-workflows-plugins-agents<2.1.0,>=2.0.0rc1; extra == 'agents'
Requires-Dist: mistralai-workflows-plugins-mistralai<2.1.0,>=2.0.0rc1; extra == 'agents'
Provides-Extra: all-plugins
Requires-Dist: mistralai-workflows-plugins-agents<2.1.0,>=2.0.0rc1; extra == 'all-plugins'
Requires-Dist: mistralai-workflows-plugins-mistralai<2.1.0,>=2.0.0rc1; extra == 'all-plugins'
Provides-Extra: mistralai
Requires-Dist: mistralai-workflows-plugins-mistralai<2.1.0,>=2.0.0rc1; extra == 'mistralai'
